viratoken
