Metadata-Version: 1.1
Name: viratoken
Version: 0.3
Summary: Small lib to encode/decode/sign/verify JWTs using asymmetric cryptography.
Home-page: https://gitlab.com/ok-br/viratoken
Author: Andrés M. R. Martano
Author-email: andres@inventati.org
License: UNKNOWN
Keywords: cryptography,jwt
Platform: UNKNOWN
Classifier: Development Status :: 4 - Beta
Classifier: Environment :: Web Environment
Classifier: Intended Audience :: Developers
Classifier: License :: OSI Approved :: GNU General Public License v3 (GPLv3)
Classifier: Operating System :: OS Independent
Classifier: Programming Language :: Python
Classifier: Programming Language :: Python :: 2
Classifier: Programming Language :: Python :: 3
Classifier: Topic :: Security :: Cryptography
Classifier: Topic :: Software Development :: Libraries :: Python Modules
Classifier: Environment :: Web Environment
